{
  "backup_id": "20260419_231314",
  "action": "update",
  "timestamp": "2026-04-19T23:13:14.840824",
  "config": {
    "weights": {
      "all_store_repurchase_rate": 0.3,
      "same_product_repurchase_rate": 0.2,
      "old_customer_gsv_ratio": 0.05,
      "old_customer_aus": 0.4,
      "recent_7d_repurchase_users": 0.05
    },
    "targets": {
      "all_store_repurchase_rate": 0.0351,
      "same_product_repurchase_rate": 0.0071,
      "old_customer_gsv_ratio": 0.4378,
      "old_customer_aus": 171.53,
      "recent_7d_repurchase_users": 289
    },
    "alert_thresholds": {
      "all_store_repurchase_rate_low": 0.1,
      "same_product_repurchase_rate_drop": 0.1,
      "old_customer_gsv_ratio_low": 0.25,
      "old_customer_aus_low": 50
    },
    "health_level_bounds": {
      "healthy": 70,
      "warning": 50
    }
  }
}